Metadata-Version: 1.0
Name: company2country-by-wjt
Version: 0.0.3
Summary: hello pypi
Home-page: UNKNOWN
Author: wujiating
Author-email: wujiating@mesalab.cn
License: UNKNOWN
Keywords: get country by company name
Platform: any
